baduk_id/__init__.py
baduk_id/baduk_id.py
baduk_id-0.1.2.dist-info/LICENSE
baduk_id-0.1.2.dist-info/METADATA
baduk_id-0.1.2.dist-info/WHEEL
baduk_id-0.1.2.dist-info/top_level.txt
baduk_id-0.1.2.dist-info/RECORD
