Metadata-Version: 2.1
Name: baduk-id
Version: 0.1.2
Summary: A set of utilities for generating a compact ID from a baduk board state.
Home-page: https://github.com/benjaminpjones/baduk-id
Author: Benjamin P. Jones
Author-email: benjaminpaikjones@gmail.com
License: UNKNOWN
Project-URL: Bug Tracker, https://github.com/benjaminpjones/baduk-id/issues
Platform: UNKNOWN
Classifier: Programming Language :: Python :: 3
Classifier: License :: OSI Approved :: MIT License
Classifier: Operating System :: OS Independent
Requires-Python: >=3.6
License-File: LICENSE
